scorify/__init__.py
scorify/aggregators.py
scorify/datafile.py
scorify/directives.py
scorify/errors.py
scorify/excel_reader.py
scorify/info.py
scorify/mappings.py
scorify/reliability.py
scorify/score_data.py
scorify/scorer.py
scorify/scoresheet.py
scorify/utils.py
scorify/scripts/__init__.py
scorify/scripts/score_data.py
scorify/scripts/score_multi.py
tests/__init__.py
tests/base.py
tests/test_aggregators.py
tests/test_datafile.py
tests/test_directives.py
tests/test_integration.py
tests/test_mappings.py
tests/test_reliability.py
tests/test_score_multi.py
tests/test_scorer.py
tests/test_scoresheet.py
tests/test_utils.py
scorify-2024.7.19.dist-info/LICENSE
scorify-2024.7.19.dist-info/METADATA
scorify-2024.7.19.dist-info/WHEEL
scorify-2024.7.19.dist-info/entry_points.txt
scorify-2024.7.19.dist-info/top_level.txt
scorify-2024.7.19.dist-info/RECORD
