Metadata-Version: 2.1
Name: scorify
Version: 2024.7.19
Summary: Library for scoring questionnaires
Home-page: https://github.com/uwmadison-chm/scorify
Download-URL: https://github.com/uwmadison-chm/scorify/releases
Author: Nate Vack
Author-email: njvack@wisc.edu
Maintainer: Nate Vack
Maintainer-email: njvack@wisc.edu
License: MIT
Platform: OS Independent
Classifier: Programming Language :: Python :: 3
Classifier: License :: OSI Approved :: MIT License
Classifier: Operating System :: OS Independent
Classifier: Topic :: Software Development :: Libraries :: Python Modules
Classifier: Topic :: Scientific/Engineering :: Information Analysis
Classifier: Development Status :: 5 - Production/Stable
Classifier: Environment :: Console
Classifier: Intended Audience :: Science/Research
Classifier: Natural Language :: English
Classifier: Operating System :: OS Independent
Provides: scorify
License-File: LICENSE
Requires-Dist: schema >=0.7.0
Requires-Dist: openpyxl >=3.0.0
Requires-Dist: docopt-ng >=0.9.0
Requires-Dist: pandas >=1.3.5
Requires-Dist: scipy >=1.7.3
